README.txt
pystockfish.py
setup.py
pystockfish.egg-info/PKG-INFO
pystockfish.egg-info/SOURCES.txt
pystockfish.egg-info/dependency_links.txt
pystockfish.egg-info/top_level.txt