Metadata-Version: 1.1
Name: pystockfish
Version: 0.1.3
Summary: Wraps the open-source Stockfish chess engine for easy integration into python.
Home-page: http://www.github.com/iamjarret/pystockfish/
Author: Jarret Petrillo
Author-email: iamjarret@gmail.com
License: GPL3
Keywords: chess stockfish
Platform: UNKNOWN
Classifier: Programming Language :: Python
Classifier: Operating System :: Unix
Classifier: License :: OSI Approved :: GNU General Public License (GPL)
Classifier: Development Status :: 2 - Pre-Alpha
Classifier: Topic :: Games/Entertainment :: Board Games
Classifier: Topic :: Software Development :: Libraries :: Python Modules
